py_pay/__init__.py
py_pay/utils.py
py_pay/alipay/__init__.py
py_pay/wechat/__init__.py
py_pay-1.3.0.dist-info/LICENSE
py_pay-1.3.0.dist-info/METADATA
py_pay-1.3.0.dist-info/WHEEL
py_pay-1.3.0.dist-info/top_level.txt
py_pay-1.3.0.dist-info/RECORD
