Metadata-Version: 2.1
Name: py-pay
Version: 1.3.0
Summary: Python pay library: alipay, wechat, etc.
Home-page: https://github.com/kerol/py-pay
Author: kerol
Author-email: ikerol@163.com
License: UNKNOWN
Platform: UNKNOWN
Classifier: Programming Language :: Python :: 3
Classifier: License :: OSI Approved :: MIT License
Classifier: Operating System :: OS Independent
Requires-Dist: requests
Requires-Dist: ujson
Requires-Dist: pycrypto
Requires-Dist: xmltodict
